stdl/__init__.py
stdl/color.py
stdl/decorators.py
stdl/dt.py
stdl/fs.py
stdl/import_lazy.py
stdl/log.py
stdl/lst.py
stdl/net.py
stdl/st.py
stdl-0.6.8.dist-info/METADATA
stdl-0.6.8.dist-info/WHEEL
stdl-0.6.8.dist-info/licenses/LICENSE
stdl-0.6.8.dist-info/RECORD
