Metadata-Version: 2.4
Name: stdl
Version: 0.6.8
Summary: Extended Python Standard Library
Project-URL: Repository, https://github.com/zigai/stdl
Project-URL: Issues, https://github.com/zigai/stdl/issues
Project-URL: Homepage, https://github.com/zigai/stdl
Author-email: Žiga Ivanšek <ziga.ivansek@gmail.com>
License: MIT License
License-File: LICENSE
Keywords: ansi-colors,color-formats,filesystem,lazy-import,list-utils,python-utilities,standard-library,stdl,terminal-links,text-processing
Classifier: Intended Audience :: Developers
Classifier: License :: OSI Approved :: MIT License
Classifier: Operating System :: OS Independent
Classifier: Programming Language :: Python
Classifier: Programming Language :: Python :: 3
Classifier: Programming Language :: Python :: 3 :: Only
Classifier: Programming Language :: Python :: 3.10
Classifier: Programming Language :: Python :: 3.11
Classifier: Programming Language :: Python :: 3.12
Classifier: Programming Language :: Python :: 3.13
Classifier: Programming Language :: Python :: 3.14
Classifier: Topic :: Software Development :: Libraries :: Python Modules
Classifier: Topic :: System :: Filesystems
Classifier: Topic :: Text Processing :: General
Classifier: Topic :: Utilities
Classifier: Typing :: Typed
Requires-Python: >=3.10
Requires-Dist: python-dateutil>=2.8.2
Requires-Dist: pyyaml>=6.0.2
Requires-Dist: toml>=0.10.2
Requires-Dist: typing-extensions>=4.0; python_version < '3.11'
Provides-Extra: dev
Requires-Dist: codespell; extra == 'dev'
Requires-Dist: coverage; extra == 'dev'
Requires-Dist: mypy; extra == 'dev'
Requires-Dist: pre-commit; extra == 'dev'
Requires-Dist: pydantic>=2; extra == 'dev'
Requires-Dist: pytest; extra == 'dev'
Requires-Dist: ruff; extra == 'dev'
Provides-Extra: full
Requires-Dist: tqdm>=4.67.1; extra == 'full'
Provides-Extra: test
Requires-Dist: coverage; extra == 'test'
Requires-Dist: pydantic>=2; extra == 'test'
Requires-Dist: pytest; extra == 'test'
